LICENSE
MANIFEST.in
README.md
fastentrypoints.py
setup.py
cognito_login/__data__.py
cognito_login/__init__.py
cognito_login/cognito_login.py
cognito_login/default_plugins.py
cognito_login.egg-info/PKG-INFO
cognito_login.egg-info/SOURCES.txt
cognito_login.egg-info/dependency_links.txt
cognito_login.egg-info/entry_points.txt
cognito_login.egg-info/requires.txt
cognito_login.egg-info/top_level.txt
cognito_login/cli/__init__.py
cognito_login/cli/main.py
cognito_login/lib/__init__.py
cognito_login/lib/exceptions.py
cognito_login/lib/get_jwt.py
cognito_login/lib/logger.py
cognito_login/lib/parse_args.py
cognito_login/lib/plugins/__init__.py
cognito_login/lib/plugins/hookimpl.py
cognito_login/lib/plugins/hookspec.py
cognito_login/lib/plugins/plugin_manager.py