Metadata-Version: 2.1
Name: cognito-login
Version: 0.0.5
Summary: cognito-login - A CLI to get a jwt from cognito login credentials
Home-page: https://github.com/trek10inc/cognito-login
Author: Trek10, Inc
Author-email: package-management@trek10.com
License: MIT
Requires-Python: >=3.5
License-File: LICENSE
